README.md
setup.py
asyncexecutor/AsyncExecutor.py
asyncexecutor/__init__.py
redismap/RedisMap.py
redismap/__init__.py
xn_wheel.egg-info/PKG-INFO
xn_wheel.egg-info/SOURCES.txt
xn_wheel.egg-info/dependency_links.txt
xn_wheel.egg-info/top_level.txt